bae_mem/__init__.py
bae_mem/exceptions.py
bae_mem/client/__init__.py
bae_mem/client/main.py
bae_mem/client/project.py
bae_mem/client/utils.py
bae_mem/configs/__init__.py
bae_mem/configs/base.py
bae_mem/configs/enums.py
bae_mem/configs/prompts.py
bae_mem/configs/embeddings/__init__.py
bae_mem/configs/embeddings/base.py
bae_mem/configs/llms/__init__.py
bae_mem/configs/llms/anthropic.py
bae_mem/configs/llms/aws_bedrock.py
bae_mem/configs/llms/azure.py
bae_mem/configs/llms/base.py
bae_mem/configs/llms/deepseek.py
bae_mem/configs/llms/lmstudio.py
bae_mem/configs/llms/ollama.py
bae_mem/configs/llms/openai.py
bae_mem/configs/llms/vllm.py
bae_mem/configs/rerankers/__init__.py
bae_mem/configs/rerankers/base.py
bae_mem/configs/rerankers/cohere.py
bae_mem/configs/rerankers/config.py
bae_mem/configs/rerankers/huggingface.py
bae_mem/configs/rerankers/llm.py
bae_mem/configs/rerankers/sentence_transformer.py
bae_mem/configs/rerankers/zero_entropy.py
bae_mem/configs/vector_stores/__init__.py
bae_mem/configs/vector_stores/azure_ai_search.py
bae_mem/configs/vector_stores/azure_mysql.py
bae_mem/configs/vector_stores/baidu.py
bae_mem/configs/vector_stores/chroma.py
bae_mem/configs/vector_stores/databricks.py
bae_mem/configs/vector_stores/elasticsearch.py
bae_mem/configs/vector_stores/faiss.py
bae_mem/configs/vector_stores/langchain.py
bae_mem/configs/vector_stores/milvus.py
bae_mem/configs/vector_stores/mongodb.py
bae_mem/configs/vector_stores/neptune.py
bae_mem/configs/vector_stores/opensearch.py
bae_mem/configs/vector_stores/pgvector.py
bae_mem/configs/vector_stores/pinecone.py
bae_mem/configs/vector_stores/qdrant.py
bae_mem/configs/vector_stores/redis.py
bae_mem/configs/vector_stores/s3_vectors.py
bae_mem/configs/vector_stores/supabase.py
bae_mem/configs/vector_stores/upstash_vector.py
bae_mem/configs/vector_stores/valkey.py
bae_mem/configs/vector_stores/vertex_ai_vector_search.py
bae_mem/configs/vector_stores/weaviate.py
bae_mem/embeddings/__init__.py
bae_mem-0.3.0.dist-info/METADATA
bae_mem-0.3.0.dist-info/WHEEL
bae_mem-0.3.0.dist-info/top_level.txt
bae_mem-0.3.0.dist-info/RECORD
