Metadata-Version: 2.4
Name: bae-mem
Version: 0.3.0
Summary: Bae memory package custom memory mcp
Author-email: Ashwin <ufoundashwin@gmail.com>
